pypi_test/__init__.py
pypi_test/pypi_test.py
pypi_test_vincent-0.1.2.dist-info/DESCRIPTION.rst
pypi_test_vincent-0.1.2.dist-info/METADATA
pypi_test_vincent-0.1.2.dist-info/RECORD
pypi_test_vincent-0.1.2.dist-info/WHEEL
pypi_test_vincent-0.1.2.dist-info/metadata.json
pypi_test_vincent-0.1.2.dist-info/top_level.txt
tests/__init__.py
tests/test_pypi_test.py
