Metadata-Version: 2.0
Name: pypi-test-vincent
Version: 0.1.2
Summary: TODO
Home-page: https://github.com/yechanggui/pypi_test
Author: Vincent yecg 
Author-email: qy2zycg@gmail.com
License: MIT license
Keywords: pypi_test_vincent
Platform: UNKNOWN
Classifier: Development Status :: 2 - Pre-Alpha
Classifier: Intended Audience :: Developers
Classifier: License :: OSI Approved :: MIT License
Classifier: Natural Language :: English
Classifier: Programming Language :: Python :: 2
Classifier: Programming Language :: Python :: 2.7
Classifier: Programming Language :: Python :: 3
Classifier: Programming Language :: Python :: 3.4
Classifier: Programming Language :: Python :: 3.5
Classifier: Programming Language :: Python :: 3.6
Classifier: Programming Language :: Python :: 3.7
